gqf/HTTP.py
gqf/__init__.py
gqf/beautify.py
gqf/crypto.py
gqf/dict.py
gqf/file.py
gqf/mouse.py
gqf/process.py
gqf/str.py
gqf/tempCodeRunnerFile.py
gqf/time.py
gqf/tk.py
gqf-2023.1.30.post5.dist-info/METADATA
gqf-2023.1.30.post5.dist-info/WHEEL
gqf-2023.1.30.post5.dist-info/top_level.txt
gqf-2023.1.30.post5.dist-info/RECORD
