Metadata-Version: 2.1
Name: gqf
Version: 2023.1.30.post5
Summary: misc functions
Author-email: gqf <guanworkmail@163.com>
Classifier: Programming Language :: Python :: 3
